Workbook

Sheet Lista de Precios
A1: VIVA PRO — LISTA DE PRECIOS Y BONO (editable)
A2: Bono del Buen Pagador 2026 — editar montos/rangos si cambia la norma
A3: Tramo | B3: Desde (S/) | C3: Hasta (S/) | D3: Bono (S/)
A4: Tramo 1 | B4: 69900 | C4: 99600 | D4: 27800
A5: Tramo 2 | B5: 99601 | C5: 149200 | D5: 23200
A6: Tramo 3 | B6: 149201 | C6: 248300 | D6: 21200
A7: Tramo 4 | B7: 248301 | C7: 367600 | D7: 7900
A9: LISTA DE PRECIOS POR DEPARTAMENTO
A10: Código | B10: Tipología | C10: Nivel | D10: Precio Lista (S/) | E10: Bono (S/)
A11: 202 | B11: 2D | C11: P2 | D11: 238000 | E11: =IF(OR(D11<$B$4,D11>$C$7),0,IF(D11<=$C$4,$D$4,IF(D11<=$C$5,$D$5,IF(D11<=$C$6,$D$6,$D$7)))) -> 21200
A12: 302 | B12: 2D | C12: P3 | D12: 234500 | E12: =IF(OR(D12<$B$4,D12>$C$7),0,IF(D12<=$C$4,$D$4,IF(D12<=$C$5,$D$5,IF(D12<=$C$6,$D$6,$D$7)))) -> 21200
A13: 402 | B13: 2D | C13: P4 | D13: 231000 | E13: =IF(OR(D13<$B$4,D13>$C$7),0,IF(D13<=$C$4,$D$4,IF(D13<=$C$5,$D$5,IF(D13<=$C$6,$D$6,$D$7)))) -> 21200
A14: 502 | B14: 2D | C14: P5 | D14: 227500 | E14: =IF(OR(D14<$B$4,D14>$C$7),0,IF(D14<=$C$4,$D$4,IF(D14<=$C$5,$D$5,IF(D14<=$C$6,$D$6,$D$7)))) -> 21200
A15: 602 | B15: 2D | C15: P6 | D15: 224000 | E15: =IF(OR(D15<$B$4,D15>$C$7),0,IF(D15<=$C$4,$D$4,IF(D15<=$C$5,$D$5,IF(D15<=$C$6,$D$6,$D$7)))) -> 21200
A16: 702 | B16: 2D | C16: P7 | D16: 220500 | E16: =IF(OR(D16<$B$4,D16>$C$7),0,IF(D16<=$C$4,$D$4,IF(D16<=$C$5,$D$5,IF(D16<=$C$6,$D$6,$D$7)))) -> 21200
A17: 802 | B17: 2D | C17: P8 | D17: 217000 | E17: =IF(OR(D17<$B$4,D17>$C$7),0,IF(D17<=$C$4,$D$4,IF(D17<=$C$5,$D$5,IF(D17<=$C$6,$D$6,$D$7)))) -> 21200
A18: 902 | B18: 2D | C18: P9 | D18: 213500 | E18: =IF(OR(D18<$B$4,D18>$C$7),0,IF(D18<=$C$4,$D$4,IF(D18<=$C$5,$D$5,IF(D18<=$C$6,$D$6,$D$7)))) -> 21200
A19: 201 | B19: 3D-B | C19: P2 | D19: 308000 | E19: =IF(OR(D19<$B$4,D19>$C$7),0,IF(D19<=$C$4,$D$4,IF(D19<=$C$5,$D$5,IF(D19<=$C$6,$D$6,$D$7)))) -> 7900
A20: 301 | B20: 3D-B | C20: P3 | D20: 304500 | E20: =IF(OR(D20<$B$4,D20>$C$7),0,IF(D20<=$C$4,$D$4,IF(D20<=$C$5,$D$5,IF(D20<=$C$6,$D$6,$D$7)))) -> 7900
A21: 401 | B21: 3D-B | C21: P4 | D21: 301000 | E21: =IF(OR(D21<$B$4,D21>$C$7),0,IF(D21<=$C$4,$D$4,IF(D21<=$C$5,$D$5,IF(D21<=$C$6,$D$6,$D$7)))) -> 7900
A22: 501 | B22: 3D-B | C22: P5 | D22: 297500 | E22: =IF(OR(D22<$B$4,D22>$C$7),0,IF(D22<=$C$4,$D$4,IF(D22<=$C$5,$D$5,IF(D22<=$C$6,$D$6,$D$7)))) -> 7900
... A37: 803D | B37: DPX B | C37: P8-9 | D37: 416500 | E37: =IF(OR(D37<$B$4,D37>$C$7),0,IF(D37<=$C$4,$D$4,IF(D37<=$C$5,$D$5,IF(D37<=$C$6,$D$6,$D$7)))) -> 0
A39: Precio editable (ámbar). El bono se recalcula solo. Fuente: Lista de precios VIVA PRO rev. 02.02.2026.

Sheet Simulador
B1: VIVA PRO — SIMULADOR DE CRÉDITO HIPOTECARIO
B2: La Haus Constructora SAC · Jr. Perseverancia, Los Olivos | K2: 10 | L2: Simple | M2: 0.075 | N2: 0.1
K3: 15 | L3: Doble | M3: 0.1 | N3: 0.15
B4: DATOS DEL CLIENTE Y DEPARTAMENTO | K4: 20 | M4: 0.15 | N4: 0.2
B5: Cliente | D5: Nombre del cliente | K5: 25 | M5: 0.2 | N5: 0.25
B6: Departamento (elige el código) | D6: 201 | N6: 0.3
B7: Tipología | D7: =IFERROR(VLOOKUP($D$6,'Lista de Precios'!$A$11:$E$37,2,FALSE()),"") -> 3D-B
B8: Plazo (años) | D8: 20
B9: Tipo de cuota | D9: Simple
B11: PARÁMETROS FINANCIEROS (editables — cambian según el banco)
B12: TEA — MiVivienda | D12: 0.09
B13: TEA — Tradicional | D13: 0.09
B14: Seguro desgravamen (mensual, % saldo) | D14: 0.00056 | E14: ◄ No mover (tasa del banco)
B15: Seguro del inmueble (anual, % valor) | D15: 0.00372 | E15: ◄ No mover (tasa del banco)
B16: Comisión recibo físico (S/) | D16: 9 | E16: ◄ No mover (tasa del banco)
B17: Cuota inicial — MiVivienda | D17: 0.2
B18: Cuota inicial — Tradicional (= MiVivienda) | D18: =D17 -> 0.2
B20: RESULTADO DE LA SIMULACIÓN
B21: Concepto | D21: MIVIVIENDA | E21: TRADICIONAL | H21: =(1+$D$12)^(1/12)-1 -> 0.0072073233 | I21: =(1+$D$13)^(1/12)-1 -> 0.0072073233
B22: Precio del departamento (S/) | D22: =VLOOKUP($D$6,'Lista de Precios'!$A$11:$E$37,4,FALSE()) -> 308000 | E22: =D22 -> 308000 | H22: =$D$8*12 -> 240 | I22: =$D$8*12 -> 240
B23: Cuota inicial (%) | D23: =D17 -> 0.2 | E23: =D18 -> 0.2 | H23: =(1-(1+H21)^(-H22))/H21 -> 113.99088 | I23: =(1-(1+I21)^(-I22))/I21 -> 113.99088
B24: Cuota inicial (S/) | D24: =D22*D23 -> 61600 | E24: =E22*E23 -> 61600 | H24: =(1+H21)^(-12)*(1-(1+H21)^(-12*$D$8))/(1-(1+H21)^(-12)) -> 9.1285457 | I24: =(1+I21)^(-12)*(1-(1+I21)^(-12*$D$8))/(1-(1+I21)^(-12)) -> 9.1285457
B25: Bono del Buen Pagador (S/) | D25: =VLOOKUP($D$6,'Lista de Precios'!$A$11:$E$37,5,FALSE()) -> 7900 | E25: 0 | H25: =H24*(1+(1+H21)^5) -> 18.590829 | I25: =I24*(1+(1+I21)^5) -> 18.590829
B26: Monto a financiar (S/) | D26: =D22-D24-D25 -> 238500 | E26: =E22-E24-E25 -> 246400 | H26: =-PMT(H21,H22,$D$26) -> 2092.2727 | I26: =-PMT(I21,I22,$E$26) -> 2161.5765
H27: =$D$26/(H23+H25) -> 1798.8907 | I27: =$E$26/(I23+I25) -> 1858.4766
B28: Cuota mensual regular (seguros + comisión) | D28: =H28+H29 -> 2330.3127 | E28: =I28+I29 -> 2404.0405 | H28: =IF($D$9="Doble",H27,H26) -> 2092.2727 | I28: =IF($D$9="Doble",I27,I26) -> 2161.5765
B29: Cuota en Julio y Diciembre (si es doble) | D29: =IF($D$9="Doble",2*H28+H29,"No aplica") -> No aplica | E29: =IF($D$9="Doble",2*I28+I29,"No aplica") -> No aplica | H29: =$D$26*$D$14+$D$22*$D$15/12+$D$16 -> 238.04 | I29: =$E$26*$D$14+$E$22*$D$15/12+$D$16 -> 242.464
B30: Ingreso neto mínimo sugerido (cuota ÷ 50%) | D30: =D28/0.5 -> 4660.6254 | E30: =E28/0.5 -> 4808.081
B31: Ingreso bruto mínimo sugerido (neto + 12%) | D31: =D30*1.12 -> 5219.9004 | E31: =E30*1.12 -> 5385.0507
B33: • Simulación REFERENCIAL. La cuota, TEA y TCEA finales dependen de la evaluación del banco, perfil crediticio y tasación.
B34: • Cuota SIMPLE: 12 cuotas iguales/año. Cuota DOBLE: en julio y diciembre se paga doble → baja la cuota regular de los otros 10 meses.
B35: • Seguros y comisión son editables (cambian según el banco). Desgravamen sobre saldo, todo riesgo sobre el valor. TEA + seguros = TCEA.
B36: • Validado contra el simulador real de BanBif: a igualdad de tasas, coincide con diferencia menor a S/2. La lista de precios está en su pestaña.

Sheet Cronograma de Pago
A1: VIVA PRO — CRONOGRAMA DE PAGO (referencial) | L1: =IF($B$3="MiVivienda",Simulador!D26,Simulador!E26) -> 238500
L2: =IF($B$3="MiVivienda",Simulador!H21,Simulador!I21) -> 0.0072073233
A3: Producto: | B3: MiVivienda | D3: =IF(B3="MiVivienda","MiVivienda (inicial + Bono)","Hipotecario tradicional") -> MiVivienda (inicial + Bono) | L3: =IF($B$3="MiVivienda",Simulador!H26,Simulador!I26) -> 2092.2727
A4: Departamento: | C4: =Simulador!D6 -> 201 | D4: Tipología: | E4: =Simulador!D7 -> 3D-B | F4: Plazo (años): | H4: =Simulador!D8 -> 20 | L4: =IF($B$3="MiVivienda",Simulador!H27,Simulador!I27) -> 1798.8907
A5: Monto a financiar: | C5: =$L$1 -> 238500 | D5: TEA: | E5: =IF($B$3="MiVivienda",Simulador!D12,Simulador!D13) -> 0.09 | F5: Tipo de cuota: | H5: =$L$10 -> Simple | L5: =Simulador!H22 -> 240
L6: =Simulador!D22 -> 308000
A7: N° Cuota | B7: Saldo inicial | C7: Cuota (cap+int) | D7: Interés | E7: Amortización | F7: Seg. Desgrav. | G7: Seg. Inmueble | H7: Comisión | I7: Cuota Total | J7: Saldo final | L7: =Simulador!D14 -> 0.00056
A8: =IF((ROW()-7)<=$L$5,(ROW()-7),"") -> 1 | B8: =IF($A8="","",$L$1) -> 238500 | C8: =IF($A8="","",IF($L$10="Doble",$L$4*IF(OR(MOD(A8,12)=7,MOD(A8,12)=0),2,1),$L$3)) -> 2092.2727 | D8: =IF($A8="","",B8*$L$2) -> 1718.9466 | E8: =IF($A8="","",C8-D8) -> 373.32608 | F8: =IF($A8="","",B8*$L$7) -> 133.56 | G8: =IF($A8="","",$L$6*$L$8/12) -> 95.48 | H8: =IF($A8="","",$L$9) -> 9 | I8: =IF($A8="","",C8+F8+G8+H8) -> 2330.3127 | J8: =IF($A8="","",B8-E8) -> 238126.67 | L8: =Simulador!D15 -> 0.00372
A9: =IF((ROW()-7)<=$L$5,(ROW()-7),"") -> 2 | B9: =IF($A9="","",J8) -> 238126.67 | C9: =IF($A9="","",IF($L$10="Doble",$L$4*IF(OR(MOD(A9,12)=7,MOD(A9,12)=0),2,1),$L$3)) -> 2092.2727 | D9: =IF($A9="","",B9*$L$2) -> 1716.2559 | E9: =IF($A9="","",C9-D9) -> 376.01676 | F9: =IF($A9="","",B9*$L$7) -> 133.35094 | G9: =IF($A9="","",$L$6*$L$8/12) -> 95.48 | H9: =IF($A9="","",$L$9) -> 9 | I9: =IF($A9="","",C9+F9+G9+H9) -> 2330.1036 | J9: =IF($A9="","",B9-E9) -> 237750.66 | L9: =Simulador!D16 -> 9
A10: =IF((ROW()-7)<=$L$5,(ROW()-7),"") -> 3 | B10: =IF($A10="","",J9) -> 237750.66 | C10: =IF($A10="","",IF($L$10="Doble",$L$4*IF(OR(MOD(A10,12)=7,MOD(A10,12)=0),2,1),$L$3)) -> 2092.2727 | D10: =IF($A10="","",B10*$L$2) -> 1713.5459 | E10: =IF($A10="","",C10-D10) -> 378.72683 | F10: =IF($A10="","",B10*$L$7) -> 133.14037 | G10: =IF($A10="","",$L$6*$L$8/12) -> 95.48 | H10: =IF($A10="","",$L$9) -> 9 | I10: =IF($A10="","",C10+F10+G10+H10) -> 2329.8931 | J10: =IF($A10="","",B10-E10) -> 237371.93 | L10: =Simulador!D9 -> Simple
A11: =IF((ROW()-7)<=$L$5,(ROW()-7),"") -> 4 | B11: =IF($A11="","",J10) -> 237371.93 | C11: =IF($A11="","",IF($L$10="Doble",$L$4*IF(OR(MOD(A11,12)=7,MOD(A11,12)=0),2,1),$L$3)) -> 2092.2727 | D11: =IF($A11="","",B11*$L$2) -> 1710.8162 | E11: =IF($A11="","",C11-D11) -> 381.45644 | F11: =IF($A11="","",B11*$L$7) -> 132.92828 | G11: =IF($A11="","",$L$6*$L$8/12) -> 95.48 | H11: =IF($A11="","",$L$9) -> 9 | I11: =IF($A11="","",C11+F11+G11+H11) -> 2329.681 | J11: =IF($A11="","",B11-E11) -> 236990.47
A12: =IF((ROW()-7)<=$L$5,(ROW()-7),"") -> 5 | B12: =IF($A12="","",J11) -> 236990.47 | C12: =IF($A12="","",IF($L$10="Doble",$L$4*IF(OR(MOD(A12,12)=7,MOD(A12,12)=0),2,1),$L$3)) -> 2092.2727 | D12: =IF($A12="","",B12*$L$2) -> 1708.067 | E12: =IF($A12="","",C12-D12) -> 384.20572 | F12: =IF($A12="","",B12*$L$7) -> 132.71467 | G12: =IF($A12="","",$L$6*$L$8/12) -> 95.48 | H12: =IF($A12="","",$L$9) -> 9 | I12: =IF($A12="","",C12+F12+G12+H12) -> 2329.4674 | J12: =IF($A12="","",B12-E12) -> 236606.27
A13: =IF((ROW()-7)<=$L$5,(ROW()-7),"") -> 6 | B13: =IF($A13="","",J12) -> 236606.27 | C13: =IF($A13="","",IF($L$10="Doble",$L$4*IF(OR(MOD(A13,12)=7,MOD(A13,12)=0),2,1),$L$3)) -> 2092.2727 | D13: =IF($A13="","",B13*$L$2) -> 1705.2979 | E13: =IF($A13="","",C13-D13) -> 386.97482 | F13: =IF($A13="","",B13*$L$7) -> 132.49951 | G13: =IF($A13="","",$L$6*$L$8/12) -> 95.48 | H13: =IF($A13="","",$L$9) -> 9 | I13: =IF($A13="","",C13+F13+G13+H13) -> 2329.2522 | J13: =IF($A13="","",B13-E13) -> 236219.29
A14: =IF((ROW()-7)<=$L$5,(ROW()-7),"") -> 7 | B14: =IF($A14="","",J13) -> 236219.29 | C14: =IF($A14="","",IF($L$10="Doble",$L$4*IF(OR(MOD(A14,12)=7,MOD(A14,12)=0),2,1),$L$3)) -> 2092.2727 | D14: =IF($A14="","",B14*$L$2) -> 1702.5088 | E14: =IF($A14="","",C14-D14) -> 389.76387 | F14: =IF($A14="","",B14*$L$7) -> 132.2828 | G14: =IF($A14="","",$L$6*$L$8/12) -> 95.48 | H14: =IF($A14="","",$L$9) -> 9 | I14: =IF($A14="","",C14+F14+G14+H14) -> 2329.0355 | J14: =IF($A14="","",B14-E14) -> 235829.53
A15: =IF((ROW()-7)<=$L$5,(ROW()-7),"") -> 8 | B15: =IF($A15="","",J14) -> 235829.53 | C15: =IF($A15="","",IF($L$10="Doble",$L$4*IF(OR(MOD(A15,12)=7,MOD(A15,12)=0),2,1),$L$3)) -> 2092.2727 | D15: =IF($A15="","",B15*$L$2) -> 1699.6997 | E15: =IF($A15="","",C15-D15) -> 392.57302 | F15: =IF($A15="","",B15*$L$7) -> 132.06454 | G15: =IF($A15="","",$L$6*$L$8/12) -> 95.48 | H15: =IF($A15="","",$L$9) -> 9 | I15: =IF($A15="","",C15+F15+G15+H15) -> 2328.8172 | J15: =IF($A15="","",B15-E15) -> 235436.96
A16: =IF((ROW()-7)<=$L$5,(ROW()-7),"") -> 9 | B16: =IF($A16="","",J15) -> 235436.96 | C16: =IF($A16="","",IF($L$10="Doble",$L$4*IF(OR(MOD(A16,12)=7,MOD(A16,12)=0),2,1),$L$3)) -> 2092.2727 | D16: =IF($A16="","",B16*$L$2) -> 1696.8703 | E16: =IF($A16="","",C16-D16) -> 395.40242 | F16: =IF($A16="","",B16*$L$7) -> 131.8447 | G16: =IF($A16="","",$L$6*$L$8/12) -> 95.48 | H16: =IF($A16="","",$L$9) -> 9 | I16: =IF($A16="","",C16+F16+G16+H16) -> 2328.5974 | J16: =IF($A16="","",B16-E16) -> 235041.55
A17: =IF((ROW()-7)<=$L$5,(ROW()-7),"") -> 10 | B17: =IF($A17="","",J16) -> 235041.55 | C17: =IF($A17="","",IF($L$10="Doble",$L$4*IF(OR(MOD(A17,12)=7,MOD(A17,12)=0),2,1),$L$3)) -> 2092.2727 | D17: =IF($A17="","",B17*$L$2) -> 1694.0205 | E17: =IF($A17="","",C17-D17) -> 398.25222 | F17: =IF($A17="","",B17*$L$7) -> 131.62327 | G17: =IF($A17="","",$L$6*$L$8/12) -> 95.48 | H17: =IF($A17="","",$L$9) -> 9 | I17: =IF($A17="","",C17+F17+G17+H17) -> 2328.376 | J17: =IF($A17="","",B17-E17) -> 234643.3
A18: =IF((ROW()-7)<=$L$5,(ROW()-7),"") -> 11 | B18: =IF($A18="","",J17) -> 234643.3 | C18: =IF($A18="","",IF($L$10="Doble",$L$4*IF(OR(MOD(A18,12)=7,MOD(A18,12)=0),2,1),$L$3)) -> 2092.2727 | D18: =IF($A18="","",B18*$L$2) -> 1691.1501 | E18: =IF($A18="","",C18-D18) -> 401.12255 | F18: =IF($A18="","",B18*$L$7) -> 131.40025 | G18: =IF($A18="","",$L$6*$L$8/12) -> 95.48 | H18: =IF($A18="","",$L$9) -> 9 | I18: =IF($A18="","",C18+F18+G18+H18) -> 2328.1529 | J18: =IF($A18="","",B18-E18) -> 234242.18
A19: =IF((ROW()-7)<=$L$5,(ROW()-7),"") -> 12 | B19: =IF($A19="","",J18) -> 234242.18 | C19: =IF($A19="","",IF($L$10="Doble",$L$4*IF(OR(MOD(A19,12)=7,MOD(A19,12)=0),2,1),$L$3)) -> 2092.2727 | D19: =IF($A19="","",B19*$L$2) -> 1688.2591 | E19: =IF($A19="","",C19-D19) -> 404.01357 | F19: =IF($A19="","",B19*$L$7) -> 131.17562 | G19: =IF($A19="","",$L$6*$L$8/12) -> 95.48 | H19: =IF($A19="","",$L$9) -> 9 | I19: =IF($A19="","",C19+F19+G19+H19) -> 2327.9283 | J19: =IF($A19="","",B19-E19) -> 233838.17
A20: =IF((ROW()-7)<=$L$5,(ROW()-7),"") -> 13 | B20: =IF($A20="","",J19) -> 233838.17 | C20: =IF($A20="","",IF($L$10="Doble",$L$4*IF(OR(MOD(A20,12)=7,MOD(A20,12)=0),2,1),$L$3)) -> 2092.2727 | D20: =IF($A20="","",B20*$L$2) -> 1685.3473 | E20: =IF($A20="","",C20-D20) -> 406.92542 | F20: =IF($A20="","",B20*$L$7) -> 130.94937 | G20: =IF($A20="","",$L$6*$L$8/12) -> 95.48 | H20: =IF($A20="","",$L$9) -> 9 | I20: =IF($A20="","",C20+F20+G20+H20) -> 2327.7021 | J20: =IF($A20="","",B20-E20) -> 233431.24
A21: =IF((ROW()-7)<=$L$5,(ROW()-7),"") -> 14 | B21: =IF($A21="","",J20) -> 233431.24 | C21: =IF($A21="","",IF($L$10="Doble",$L$4*IF(OR(MOD(A21,12)=7,MOD(A21,12)=0),2,1),$L$3)) -> 2092.2727 | D21: =IF($A21="","",B21*$L$2) -> 1682.4144 | E21: =IF($A21="","",C21-D21) -> 409.85827 | F21: =IF($A21="","",B21*$L$7) -> 130.72149 | G21: =IF($A21="","",$L$6*$L$8/12) -> 95.48 | H21: =IF($A21="","",$L$9) -> 9 | I21: =IF($A21="","",C21+F21+G21+H21) -> 2327.4742 | J21: =IF($A21="","",B21-E21) -> 233021.38
A22: =IF((ROW()-7)<=$L$5,(ROW()-7),"") -> 15 | B22: =IF($A22="","",J21) -> 233021.38 | C22: =IF($A22="","",IF($L$10="Doble",$L$4*IF(OR(MOD(A22,12)=7,MOD(A22,12)=0),2,1),$L$3)) -> 2092.2727 | D22: =IF($A22="","",B22*$L$2) -> 1679.4604 | E22: =IF($A22="","",C22-D22) -> 412.81225 | F22: =IF($A22="","",B22*$L$7) -> 130.49197 | G22: =IF($A22="","",$L$6*$L$8/12) -> 95.48 | H22: =IF($A22="","",$L$9) -> 9 | I22: =IF($A22="","",C22+F22+G22+H22) -> 2327.2447 | J22: =IF($A22="","",B22-E22) -> 232608.57
... A307: =IF((ROW()-7)<=$L$5,(ROW()-7),"") | B307: =IF($A307="","",J306) | C307: =IF($A307="","",IF($L$10="Doble",$L$4*IF(OR(MOD(A307,12)=7,MOD(A307,12)=0),2,1),$L$3)) | D307: =IF($A307="","",B307*$L$2) | E307: =IF($A307="","",C307-D307) | F307: =IF($A307="","",B307*$L$7) | G307: =IF($A307="","",$L$6*$L$8/12) | H307: =IF($A307="","",$L$9) | I307: =IF($A307="","",C307+F307+G307+H307) | J307: =IF($A307="","",B307-E307)
A309: Cronograma referencial — método cuota fija (sistema francés). Cambia el producto en la celda ámbar; el cronograma se recalcula solo según el escenario del Simulador.
